opensea_wrapper/__init__.py
opensea_wrapper/wrapper.py
opensea_wrapper-0.0.1.dist-info/METADATA
opensea_wrapper-0.0.1.dist-info/WHEEL
opensea_wrapper-0.0.1.dist-info/top_level.txt
opensea_wrapper-0.0.1.dist-info/RECORD
